virtualbox/__about__.py
virtualbox/__init__.py
virtualbox/events.py
virtualbox/library.py
virtualbox/library_base.py
virtualbox/pool.py
virtualbox/utils.py
virtualbox/library_ext/__init__.py
virtualbox/library_ext/appliance.py
virtualbox/library_ext/console.py
virtualbox/library_ext/event_source.py
virtualbox/library_ext/guest.py
virtualbox/library_ext/guest_process.py
virtualbox/library_ext/guest_session.py
virtualbox/library_ext/host.py
virtualbox/library_ext/keyboard.py
virtualbox/library_ext/machine.py
virtualbox/library_ext/mouse.py
virtualbox/library_ext/process.py
virtualbox/library_ext/progress.py
virtualbox/library_ext/session.py
virtualbox/library_ext/vbox.py
virtualbox/library_ext/virtual_system_description.py
virtualbox-2.1.1.dist-info/LICENSE
virtualbox-2.1.1.dist-info/METADATA
virtualbox-2.1.1.dist-info/WHEEL
virtualbox-2.1.1.dist-info/top_level.txt
virtualbox-2.1.1.dist-info/RECORD
