Metadata-Version: 1.2
Name: virtualbox
Version: 2.1.1
Summary: Complete implementation of VirtualBox's COM API with a Pythonic interface
Home-page: https://github.com/sethmlarson/virtualbox-python
Author: Michael Dorman
Author-email: mjdorma+pyvbox@gmail.com
Maintainer: Seth Michael Larson
Maintainer-email: sethmichaellarson@gmail.com
License: Apache-2.0
Platform: cygwin
Platform: win
Platform: linux
Classifier: Development Status :: 5 - Production/Stable
Classifier: Intended Audience :: Developers
Classifier: Intended Audience :: Information Technology
Classifier: Intended Audience :: System Administrators
Classifier: Natural Language :: English
Classifier: License :: OSI Approved :: Apache Software License
Classifier: Operating System :: Microsoft
Classifier: Operating System :: POSIX
Classifier: Operating System :: MacOS
Classifier: Programming Language :: Python
Classifier: Programming Language :: Python :: 2.7
Classifier: Programming Language :: Python :: 3
Classifier: Programming Language :: Python :: 3.4
Classifier: Programming Language :: Python :: 3.5
Classifier: Programming Language :: Python :: 3.6
Classifier: Programming Language :: Python :: 3.7
Classifier: Programming Language :: Python :: Implementation :: CPython
Classifier: Topic :: Security
Classifier: Topic :: Scientific/Engineering :: Visualization
Classifier: Topic :: System :: Clustering
Classifier: Topic :: System :: Distributed Computing
Classifier: Topic :: System :: Emulators
Classifier: Topic :: Software Development :: Testing
